pwndocapi/API.py
pwndocapi/__init__.py
pwndocapi/api/__init__.py
pwndocapi/api/audits.py
pwndocapi/api/clients.py
pwndocapi/api/companies.py
pwndocapi/api/data.py
pwndocapi/api/errors.py
pwndocapi/api/users.py
pwndocapi/api/vulnerabilities.py
pwndocapi/models/Audit.py
pwndocapi/models/AuditError.py
pwndocapi/models/Finding.py
pwndocapi/models/Priority.py
pwndocapi/models/RemediationComplexity.py
pwndocapi/models/User.py
pwndocapi/models/__init__.py
pwndocapi/pwndoc.py
pwndocapi-1.3.4.dist-info/LICENSE
pwndocapi-1.3.4.dist-info/METADATA
pwndocapi-1.3.4.dist-info/WHEEL
pwndocapi-1.3.4.dist-info/entry_points.txt
pwndocapi-1.3.4.dist-info/RECORD
